torch_audit/__about__.py
torch_audit/__init__.py
torch_audit/__main__.py
torch_audit/api.py
torch_audit/cli.py
torch_audit/config.py
torch_audit/context.py
torch_audit/core.py
torch_audit/loader.py
torch_audit/py.typed
torch_audit/registry.py
torch_audit/reporters/__init__.py
torch_audit/reporters/base.py
torch_audit/reporters/console.py
torch_audit/reporters/json.py
torch_audit/reporters/sarif.py
torch_audit/runner.py
torch_audit/runtime.py
torch_audit/utils/__init__.py
torch_audit/utils/fingerprints.py
torch_audit/utils/sanitize.py
torch_audit/utils/torch_safe.py
torch_audit/validator.py
torch_audit/validators/__init__.py
torch_audit/validators/builtin/__init__.py
torch_audit/validators/builtin/activation.py
torch_audit/validators/builtin/architecture.py
torch_audit/validators/builtin/data.py
torch_audit/validators/builtin/graph.py
torch_audit/validators/builtin/hardware.py
torch_audit/validators/builtin/optimization.py
torch_audit/validators/builtin/perf.py
torch_audit/validators/builtin/practices.py
torch_audit/validators/builtin/stability.py
torch_audit/validators/builtin_loader.py
torch_audit-0.3.0.dist-info/entry_points.txt
torch_audit-0.3.0.dist-info/LICENSE
torch_audit-0.3.0.dist-info/METADATA
torch_audit-0.3.0.dist-info/WHEEL
torch_audit-0.3.0.dist-info/RECORD
