Metadata-Version: 2.3
Name: torch-audit
Version: 0.3.0
Summary: The Linter for PyTorch: Detects silent training bugs.
License: MIT
Keywords: pytorch,audit,debugging,linter,deep-learning
Author: Roman Malkiv
Author-email: malkiv.roman@gmail.com
Requires-Python: >=3.10,<4.0
Classifier: Development Status :: 4 - Beta
Classifier: Intended Audience :: Developers
Classifier: Intended Audience :: Science/Research
Classifier: License :: OSI Approved :: MIT License
Classifier: Programming Language :: Python :: 3
Classifier: Programming Language :: Python :: 3.10
Classifier: Programming Language :: Python :: 3.11
Classifier: Programming Language :: Python :: 3.12
Classifier: Programming Language :: Python :: 3.13
Classifier: Topic :: Scientific/Engineering :: Artificial Intelligence
Classifier: Typing :: Typed
Provides-Extra: all
Provides-Extra: hf
Provides-Extra: lightning
Requires-Dist: accelerate (>=0.20.0) ; extra == "hf" or extra == "all"
Requires-Dist: click (>=8.1.0,<9.0.0)
Requires-Dist: datasets (>=2.10.0) ; extra == "hf" or extra == "all"
Requires-Dist: lightning (>=2.0.0) ; extra == "lightning" or extra == "all"
Requires-Dist: numpy (>=1.20.0) ; extra == "all"
Requires-Dist: rich (>=12.0.0)
Requires-Dist: torch (>=2.0.0)
Requires-Dist: transformers (>=4.30.0) ; extra == "hf" or extra == "all"
Project-URL: Changelog, https://github.com/RMalkiv/torch-audit/blob/main/CHANGELOG.md
Project-URL: Homepage, https://github.com/RMalkiv/torch-audit
Project-URL: Issues, https://github.com/RMalkiv/torch-audit/issues
Project-URL: Repository, https://github.com/RMalkiv/torch-audit
